fastplbf/FastPLBF.py
fastplbf/FastPLBF_M.py
fastplbf/FastPLBFpp.py
fastplbf/FastPLBFpp_M.py
fastplbf/PLBF.py
fastplbf/PLBF_M.py
fastplbf/__init__.py
fastplbf/const.py
fastplbf/test.py
fastplbf/utils.py
fastplbftest-0.1.0.dist-info/LICENSE
fastplbftest-0.1.0.dist-info/METADATA
fastplbftest-0.1.0.dist-info/WHEEL
fastplbftest-0.1.0.dist-info/top_level.txt
fastplbftest-0.1.0.dist-info/RECORD
