Metadata-Version: 2.1
Name: fastplbftest
Version: 0.1.0
Summary: Fast PLBF: Partitioned Learned Bloom Filter with fast construction.
Home-page: https://github.com/atsukisato/FastPLBF
Author: Atsuki Sato
Author-email: sato.a.20010310@gmail.com
Maintainer: Atsuki Sato
Maintainer-email: sato.a.20010310@gmail.com
License: MIT
Keywords: bloom filter,learned index
Platform: UNKNOWN
Classifier: License :: OSI Approved :: MIT License
Classifier: Development Status :: 3 - Alpha
Classifier: Intended Audience :: Developers
Classifier: Intended Audience :: Information Technology
Classifier: Intended Audience :: Science/Research
Classifier: Programming Language :: Python :: 3.9
Classifier: Topic :: Database
Classifier: Topic :: Scientific/Engineering
Classifier: Topic :: Software Development
Requires-Dist: bloom-filter
